<?xml version="1.0" encoding="UTF-8"?>

<metadata xmlns:geonet="http://www.fao.org/geonetwork" xml:lang="en">
  <Esri>
    <CreaDate>20110407</CreaDate>
    <CreaTime>14232300</CreaTime>
    <SyncOnce>FALSE</SyncOnce>
    <DataProperties>
      <lineage>
        <Process ToolSource="C:\ArcGIS\ArcToolbox\Toolboxes\Data Management Tools.tbx\CreateFeatureclass" Date="20100129" Time="092452">CreateFeatureclass N:\data\metadata\templates nrri_general POLYGON # DISABLED DISABLED # # 0 0 0 N:\data\metadata\templates\nrri_general.shp</Process>
      </lineage>
    </DataProperties>
    <SyncDate>20110407</SyncDate>
    <SyncTime>14294700</SyncTime>
    <ModDate>20110407</ModDate>
    <ModTime>14371100</ModTime>
    <MetaID>{925000CF-567A-456C-8541-7B1692CEC1DA}</MetaID>
  </Esri>
  <idinfo>
    <native Sync="TRUE">Microsoft Windows XP Version 5.1 (Build 2600) Service Pack 3; ESRI ArcCatalog 9.3.0.1770</native>
    <descript>
      <langdata Sync="TRUE">en</langdata>
      <abstract>Footprints of sites from which field data was used and regions for which Performance Indicators are considered applicable in the 2010 Upper Great Lakes water level study.</abstract>
      <purpose>Footprints of sites from which field data was used and regions for which Performance Indicators are considered applicable in the 2010 Upper Great Lakes water level study.</purpose>
    </descript>
    <citation>
      <citeinfo>
        <origin>Natural Resources Research Institute, Univerisity of Minnesota, Duluth</origin>
        <pubdate />
        <title>UGLWL environmental sites and regions</title>
        <ftname Sync="TRUE">site</ftname>
        <geoform Sync="TRUE">vector digital data</geoform>
      </citeinfo>
    </citation>
    <timeperd>
      <current>publication date</current>
      <timeinfo>
        <sngdate>
          <caldate>2010</caldate>
        </sngdate>
      </timeinfo>
    </timeperd>
    <status>
      <progress>Complete</progress>
      <update>None planned</update>
    </status>
    <spdom>
      <bounding>
        <westbc Sync="TRUE">-92.944336</westbc>
        <eastbc Sync="TRUE">-78.398437</eastbc>
        <northbc Sync="TRUE">48.848225</northbc>
        <southbc Sync="TRUE">40.847060</southbc>
      </bounding>
      <lboundng>
        <leftbc Sync="TRUE">-92.944336</leftbc>
        <rightbc Sync="TRUE">-78.398437</rightbc>
        <bottombc Sync="TRUE">40.847060</bottombc>
        <topbc Sync="TRUE">48.848225</topbc>
      </lboundng>
    </spdom>
    <keywords>
      <theme>
        <themekt>REQUIRED: Reference to a formally registered thesaurus or a similar authoritative source of theme keywords.</themekt>
        <themekey>wetland</themekey>
        <themekey>water level</themekey>
        <themekey>study site</themekey>
      </theme>
    </keywords>
    <accconst>Public</accconst>
    <useconst>None</useconst>
    <natvform Sync="TRUE">Shapefile</natvform>
    <ptcontac>
      <cntinfo>
        <cntperp>
          <cntper>Terry Brown</cntper>
        </cntperp>
        <cntaddr>
          <addrtype>mailing and physical address</addrtype>
          <address>5013 Miller Trunk Highway</address>
          <city>Duluth</city>
          <state>MN</state>
          <postal>55811</postal>
          <country>USA</country>
        </cntaddr>
        <cntvoice>218-720-4345</cntvoice>
        <cntemail>tbrown@nrri.umn.edu</cntemail>
      </cntinfo>
    </ptcontac>
    <datacred>2010 Upper Great Lakes water level study Environmental TWG</datacred>
  </idinfo>
  <dataIdInfo>
    <envirDesc Sync="TRUE">Microsoft Windows XP Version 5.1 (Build 2600) Service Pack 3; ESRI ArcCatalog 9.3.0.1770</envirDesc>
    <dataLang>
      <languageCode Sync="TRUE" value="en" />
    </dataLang>
    <idCitation>
      <resTitle Sync="TRUE">site</resTitle>
      <presForm>
        <PresFormCd Sync="TRUE" value="005" />
      </presForm>
    </idCitation>
    <spatRpType>
      <SpatRepTypCd Sync="TRUE" value="001" />
    </spatRpType>
    <dataExt>
      <geoEle>
        <GeoBndBox esriExtentType="native">
          <westBL Sync="TRUE">-92.944336</westBL>
          <eastBL Sync="TRUE">-78.398437</eastBL>
          <northBL Sync="TRUE">48.848225</northBL>
          <southBL Sync="TRUE">40.84706</southBL>
          <exTypeCode Sync="TRUE">1</exTypeCode>
        </GeoBndBox>
      </geoEle>
    </dataExt>
    <geoBox esriExtentType="decdegrees">
      <westBL Sync="TRUE">-92.944336</westBL>
      <eastBL Sync="TRUE">-78.398437</eastBL>
      <northBL Sync="TRUE">48.848225</northBL>
      <southBL Sync="TRUE">40.84706</southBL>
      <exTypeCode Sync="TRUE">1</exTypeCode>
    </geoBox>
  </dataIdInfo>
  <metainfo>
    <langmeta Sync="TRUE">en</langmeta>
    <metstdn Sync="TRUE">FGDC Content Standards for Digital Geospatial Metadata</metstdn>
    <metstdv Sync="TRUE">FGDC-STD-001-1998</metstdv>
    <mettc Sync="TRUE">local time</mettc>
    <metc>
      <cntinfo>
        <cntorgp />
        <cntaddr>
          <addrtype />
          <city />
          <state />
          <postal />
        </cntaddr>
        <cntvoice />
      </cntinfo>
    </metc>
    <metd Sync="TRUE">20110407</metd>
    <metextns>
      <metprof Sync="TRUE">ESRI Metadata Profile</metprof>
    </metextns>
  </metainfo>
  <mdLang>
    <languageCode Sync="TRUE" value="en" />
  </mdLang>
  <mdStanName Sync="TRUE">ISO 19115 Geographic Information - Metadata</mdStanName>
  <mdStanVer Sync="TRUE">DIS_ESRI1.0</mdStanVer>
  <mdChar>
    <CharSetCd Sync="TRUE" value="004" />
  </mdChar>
  <mdHrLv>
    <ScopeCd Sync="TRUE" value="005" />
  </mdHrLv>
  <mdHrLvName Sync="TRUE">dataset</mdHrLvName>
  <distinfo>
    <resdesc Sync="TRUE">Downloadable Data</resdesc>
    <distliab>Disclaimer. The Great Lakes Information Network (GLIN) cannot assume liability for any damages caused by any errors or omissions in the data, nor as a result of the failure of the data to function on a particular system. The Great Lakes Information Network (GLIN) makes no warranty, expressed or implied, nor does the fact of distribution constitute such a warranty.</distliab>
    <stdorder>
      <digform>
        <digtinfo>
          <transize Sync="TRUE">0.008</transize>
        </digtinfo>
      </digform>
    </stdorder>
  </distinfo>
  <distInfo>
    <distributor>
      <distorTran>
        <onLineSrc>
          <orDesc Sync="TRUE">002</orDesc>
          <linkage Sync="TRUE" />
          <protocol Sync="TRUE">Local Area Network</protocol>
        </onLineSrc>
        <transSize Sync="TRUE">0.008</transSize>
      </distorTran>
      <distorFormat>
        <formatName Sync="TRUE">Shapefile</formatName>
      </distorFormat>
    </distributor>
  </distInfo>
  <spdoinfo>
    <direct Sync="TRUE">Vector</direct>
    <ptvctinf>
      <esriterm Name="site">
        <efeatyp Sync="TRUE">Simple</efeatyp>
        <efeageom Sync="TRUE">Polygon</efeageom>
        <esritopo Sync="TRUE">FALSE</esritopo>
        <efeacnt Sync="TRUE">37</efeacnt>
        <spindex Sync="TRUE">FALSE</spindex>
        <linrefer Sync="TRUE">FALSE</linrefer>
      </esriterm>
      <sdtsterm Name="site">
        <sdtstype Sync="TRUE">G-polygon</sdtstype>
        <ptvctcnt Sync="TRUE">37</ptvctcnt>
      </sdtsterm>
    </ptvctinf>
  </spdoinfo>
  <spatRepInfo>
    <VectSpatRep>
      <topLvl>
        <TopoLevCd Sync="TRUE" value="001" />
      </topLvl>
      <geometObjs Name="site">
        <geoObjTyp>
          <GeoObjTypCd Sync="TRUE" value="001" />
        </geoObjTyp>
        <geoObjCnt Sync="TRUE">37</geoObjCnt>
      </geometObjs>
    </VectSpatRep>
  </spatRepInfo>
  <eainfo>
    <detailed Name="site">
      <enttyp>
        <enttypl Sync="TRUE">site</enttypl>
        <enttypt Sync="TRUE">Feature Class</enttypt>
        <enttypc Sync="TRUE">37</enttypc>
      </enttyp>
      <attr>
        <attrlabl Sync="TRUE">FID</attrlabl>
        <attrdef Sync="TRUE">Internal feature number.</attrdef>
        <attrdefs Sync="TRUE">ESRI</attrdefs>
        <attrdomv>
          <udom Sync="TRUE">Sequential unique whole numbers that are automatically generated.</udom>
        </attrdomv>
        <begdatea />
      </attr>
      <attr>
        <attrlabl Sync="TRUE">Shape</attrlabl>
        <attrdef Sync="TRUE">Feature geometry.</attrdef>
        <attrdefs Sync="TRUE">ESRI</attrdefs>
        <attrdomv>
          <udom Sync="TRUE">Coordinates defining the features.</udom>
        </attrdomv>
        <begdatea />
      </attr>
      <attr>
        <attrlabl Sync="TRUE">SITE</attrlabl>
        <attrdef>Unique site ID, not used</attrdef>
        <begdatea />
      </attr>
      <attr>
        <attrlabl Sync="TRUE">NAME</attrlabl>
        <attrdef>Name of site</attrdef>
        <begdatea />
      </attr>
      <attr>
        <attrlabl Sync="TRUE">MAPPABLE</attrlabl>
        <attrdef>Internal use</attrdef>
        <begdatea />
      </attr>
    </detailed>
  </eainfo>
  <mdDateSt Sync="TRUE">20110407</mdDateSt>
  <dataqual>
    <lineage>
      <procstep>
        <procdesc Sync="TRUE">Dataset copied.</procdesc>
        <srcused Sync="TRUE">N:\data\metadata\templates\nrri_general</srcused>
        <procdate Sync="TRUE">20100129</procdate>
        <proctime Sync="TRUE">09442400</proctime>
      </procstep>
      <procstep>
        <procdesc Sync="TRUE">Metadata imported.</procdesc>
        <srcused Sync="TRUE">N:\data\metadata\templates\nrri_tnb.shp.xml</srcused>
        <procdate Sync="TRUE">20110407</procdate>
        <proctime Sync="TRUE">14232300</proctime>
      </procstep>
    </lineage>
  </dataqual>
  <spref>
    <horizsys>
      <geograph>
        <geogunit Sync="TRUE" />
        <latres Sync="TRUE">0.000000</latres>
        <longres Sync="TRUE">0.000000</longres>
      </geograph>
      <geodetic>
        <horizdn Sync="TRUE">WGS_1984</horizdn>
        <ellips Sync="TRUE">WGS 84</ellips>
        <semiaxis Sync="TRUE">6378137.000000</semiaxis>
        <denflat Sync="TRUE">298.257224</denflat>
      </geodetic>
    </horizsys>
  </spref>
  <refSysInfo>
    <RefSystem>
      <refSysID>
        <identCode Sync="TRUE">WGS 84</identCode>
      </refSysID>
    </RefSystem>
  </refSysInfo>
</metadata>